{
  "version": 2,
  "extractor": "pdffigures2",
  "figures": [
    {
      "url": "assets/figures/arxiv/2605.03618v1/fig-001.webp",
      "caption": "Figure 2: Subtask 2 Validation Results over the Strict Micro F1 metric",
      "page": 6,
      "index": 1,
      "width": 439,
      "height": 307
    },
    {
      "url": "assets/figures/arxiv/2605.03618v1/fig-002.webp",
      "caption": "Figure 3: Subtask 3 Validation Results using an average score of the metrics: BLEU, ROUGE, SARI, BERTScore, AlignScore, and MEDCON",
      "page": 6,
      "index": 2,
      "width": 442,
      "height": 374
    },
    {
      "url": "assets/figures/arxiv/2605.03618v1/fig-003.webp",
      "caption": "Figure 4: Subtask 4 Validation Results",
      "page": 7,
      "index": 3,
      "width": 442,
      "height": 441
    },
    {
      "url": "assets/figures/arxiv/2605.03618v1/fig-004.webp",
      "caption": "Figure 7: Subtask 4 Validation Results (All Models)",
      "page": 14,
      "index": 4,
      "width": 928,
      "height": 1406
    },
    {
      "url": "assets/figures/arxiv/2605.03618v1/fig-005.webp",
      "caption": "Figure 6: Subtask 3 Validation Results (All Models)",
      "page": 13,
      "index": 5,
      "width": 928,
      "height": 1022
    },
    {
      "url": "assets/figures/arxiv/2605.03618v1/fig-006.webp",
      "caption": "Figure 5: Subtask 1 Validation Results (All Models)",
      "page": 12,
      "index": 6,
      "width": 928,
      "height": 1406
    },
    {
      "url": "assets/figures/arxiv/2605.03618v1/fig-007.webp",
      "caption": "Figure 1: Subtask 1 Validation Results showing the different prompts over several different open and close source models. The scores represent the official evaluation metrics of the average of ROUGE, BERTScore, AlignScore, and MEDCON.",
      "page": 5,
      "index": 7,
      "width": 442,
      "height": 374
    }
  ]
}