{
  "version": 2,
  "extractor": "papercropper",
  "figures": [
    {
      "url": "assets/figures/openreview/openreview-icml-2025-pjadknuson/fig-001.webp",
      "caption": "",
      "page": 0,
      "index": 1,
      "width": 1676,
      "height": 818,
      "label": "Figure"
    },
    {
      "url": "assets/figures/openreview/openreview-icml-2025-pjadknuson/fig-002.webp",
      "caption": "",
      "page": 0,
      "index": 2,
      "width": 1661,
      "height": 816,
      "label": "Figure"
    },
    {
      "url": "assets/figures/openreview/openreview-icml-2025-pjadknuson/fig-003.webp",
      "caption": "",
      "page": 0,
      "index": 3,
      "width": 1594,
      "height": 919,
      "label": "Figure"
    },
    {
      "url": "assets/figures/openreview/openreview-icml-2025-pjadknuson/fig-004.webp",
      "caption": "",
      "page": 0,
      "index": 4,
      "width": 1587,
      "height": 904,
      "label": "Figure"
    },
    {
      "url": "assets/figures/openreview/openreview-icml-2025-pjadknuson/fig-005.webp",
      "caption": "",
      "page": 0,
      "index": 5,
      "width": 1568,
      "height": 917,
      "label": "Figure"
    },
    {
      "url": "assets/figures/openreview/openreview-icml-2025-pjadknuson/fig-006.webp",
      "caption": "",
      "page": 0,
      "index": 6,
      "width": 1565,
      "height": 912,
      "label": "Figure"
    },
    {
      "url": "assets/figures/openreview/openreview-icml-2025-pjadknuson/fig-007.webp",
      "caption": "",
      "page": 0,
      "index": 7,
      "width": 1568,
      "height": 913,
      "label": "Figure"
    },
    {
      "url": "assets/figures/openreview/openreview-icml-2025-pjadknuson/fig-008.webp",
      "caption": "",
      "page": 0,
      "index": 8,
      "width": 1571,
      "height": 913,
      "label": "Figure"
    },
    {
      "url": "assets/figures/openreview/openreview-icml-2025-pjadknuson/fig-009.webp",
      "caption": "",
      "page": 0,
      "index": 9,
      "width": 1570,
      "height": 910,
      "label": "Figure"
    },
    {
      "url": "assets/figures/openreview/openreview-icml-2025-pjadknuson/fig-010.webp",
      "caption": "",
      "page": 0,
      "index": 10,
      "width": 1567,
      "height": 910,
      "label": "Figure"
    },
    {
      "url": "assets/figures/openreview/openreview-icml-2025-pjadknuson/fig-011.webp",
      "caption": "",
      "page": 0,
      "index": 11,
      "width": 1572,
      "height": 916,
      "label": "Figure"
    },
    {
      "url": "assets/figures/openreview/openreview-icml-2025-pjadknuson/fig-012.webp",
      "caption": "",
      "page": 0,
      "index": 12,
      "width": 1568,
      "height": 914,
      "label": "Figure"
    }
  ]
}